Workbook

Sheet Inputs
A1: Weeks | B1: Trips | C1: Price | D1: Cost Per Ride
A2: 1 | B2: 10000 | C2: 15 | D2: 10
A3: 2 | B3: 10300 | C3: 15 | D3: 10
A4: 3 | B4: 10800 | C4: 16 | D4: 10
A5: 4 | B5: 10500 | C5: 17 | D5: 10
A6: 5 | B6: 9800 | C6: 14 | D6: 10
A7: 6 | B7: 10200 | C7: 15 | D7: 10
A8: 7 | B8: 11000 | C8: 16 | D8: 10
A9: 8 | B9: 11200 | C9: 17 | D9: 10
A10: 9 | B10: 9500 | C10: 14 | D10: 10
A11: 10 | B11: 10000 | C11: 15 | D11: 10
A12: 11 | B12: 10700 | C12: 16 | D12: 10
A13: 12 | B13: 10900 | C13: 17 | D13: 10

Sheet Calculations
A1: Week | B1: Trips | C1: Price | D1: Revenue | E1: Cost | F1: Profit | G1: Margin
A2: =Inputs!A2 -> 1 | B2: =Inputs!B2 -> 10000 | C2: =Inputs!C2 -> 15 | D2: =B2*C2 -> 150000 | E2: =B2*Inputs!D2 -> 100000 | F2: =D2-E2 -> 50000 | G2: =F2/D2 -> 0.33333333
A3: =Inputs!A3 -> 2 | B3: =Inputs!B3 -> 10300 | C3: =Inputs!C3 -> 15 | D3: =B3*C3 -> 154500 | E3: =B3*Inputs!D3 -> 103000 | F3: =D3-E3 -> 51500 | G3: =F3/D3 -> 0.33333333
A4: =Inputs!A4 -> 3 | B4: =Inputs!B4 -> 10800 | C4: =Inputs!C4 -> 16 | D4: =B4*C4 -> 172800 | E4: =B4*Inputs!D4 -> 108000 | F4: =D4-E4 -> 64800 | G4: =F4/D4 -> 0.375
A5: =Inputs!A5 -> 4 | B5: =Inputs!B5 -> 10500 | C5: =Inputs!C5 -> 17 | D5: =B5*C5 -> 178500 | E5: =B5*Inputs!D5 -> 105000 | F5: =D5-E5 -> 73500 | G5: =F5/D5 -> 0.41176471
A6: =Inputs!A6 -> 5 | B6: =Inputs!B6 -> 9800 | C6: =Inputs!C6 -> 14 | D6: =B6*C6 -> 137200 | E6: =B6*Inputs!D6 -> 98000 | F6: =D6-E6 -> 39200 | G6: =F6/D6 -> 0.28571429
A7: =Inputs!A7 -> 6 | B7: =Inputs!B7 -> 10200 | C7: =Inputs!C7 -> 15 | D7: =B7*C7 -> 153000 | E7: =B7*Inputs!D7 -> 102000 | F7: =D7-E7 -> 51000 | G7: =F7/D7 -> 0.33333333
A8: =Inputs!A8 -> 7 | B8: =Inputs!B8 -> 11000 | C8: =Inputs!C8 -> 16 | D8: =B8*C8 -> 176000 | E8: =B8*Inputs!D8 -> 110000 | F8: =D8-E8 -> 66000 | G8: =F8/D8 -> 0.375
A9: =Inputs!A9 -> 8 | B9: =Inputs!B9 -> 11200 | C9: =Inputs!C9 -> 17 | D9: =B9*C9 -> 190400 | E9: =B9*Inputs!D9 -> 112000 | F9: =D9-E9 -> 78400 | G9: =F9/D9 -> 0.41176471
A10: =Inputs!A10 -> 9 | B10: =Inputs!B10 -> 9500 | C10: =Inputs!C10 -> 14 | D10: =B10*C10 -> 133000 | E10: =B10*Inputs!D10 -> 95000 | F10: =D10-E10 -> 38000 | G10: =F10/D10 -> 0.28571429
A11: =Inputs!A11 -> 10 | B11: =Inputs!B11 -> 10000 | C11: =Inputs!C11 -> 15 | D11: =B11*C11 -> 150000 | E11: =B11*Inputs!D11 -> 100000 | F11: =D11-E11 -> 50000 | G11: =F11/D11 -> 0.33333333
A12: =Inputs!A12 -> 11 | B12: =Inputs!B12 -> 10700 | C12: =Inputs!C12 -> 16 | D12: =B12*C12 -> 171200 | E12: =B12*Inputs!D12 -> 107000 | F12: =D12-E12 -> 64200 | G12: =F12/D12 -> 0.375
A13: =Inputs!A13 -> 12 | B13: =Inputs!B13 -> 10900 | C13: =Inputs!C13 -> 17 | D13: =B13*C13 -> 185300 | E13: =B13*Inputs!D13 -> 109000 | F13: =D13-E13 -> 76300 | G13: =F13/D13 -> 0.41176471

Sheet Scenarios
A1: Scenario | B1: Price | C1: Trips | D1: Revenue
A2: Low Price | B2: 13 | C2: 11500 | D2: =B2*C2 -> 149500
A3: Base Price | B3: 15 | C3: 10000 | D3: =B3*C3 -> 150000
A4: High Price | B4: 18 | C4: 9200 | D4: =B4*C4 -> 165600

Sheet Decision
A1: Objective: Analyze how pricing impacts revenue and demand using an Uber-style model.
A2: Key Finding: Higher prices reduce trips but can increase total revenue. Lower prices increase trips but reduce margins.
A3: Insight: Revenue is maximized when pricing is balanced with demand, not when trips are maximized.
A4: Weak Point: Static pricing may miss revenue opportunities during high-demand periods.
A5: Recommendation: Increase pricing during high-demand periods to improve revenue while maintaining sufficient trip volume.
A6: Impact: Higher revenue and improved margins.
